venv/Lib/site-packages/_distutils_hack/__init__.py
venv/Lib/site-packages/_distutils_hack/override.py
venv/Lib/site-packages/build/__init__.py
venv/Lib/site-packages/build/__main__.py
venv/Lib/site-packages/build/_builder.py
venv/Lib/site-packages/build/_ctx.py
venv/Lib/site-packages/build/_exceptions.py
venv/Lib/site-packages/build/_types.py
venv/Lib/site-packages/build/_util.py
venv/Lib/site-packages/build/env.py
venv/Lib/site-packages/build/py.typed
venv/Lib/site-packages/build/util.py
venv/Lib/site-packages/build/_compat/__init__.py
venv/Lib/site-packages/build/_compat/importlib.py
venv/Lib/site-packages/build/_compat/tarfile.py
venv/Lib/site-packages/build/_compat/tomllib.py
venv/Lib/site-packages/colorama/__init__.py
venv/Lib/site-packages/colorama/ansi.py
venv/Lib/site-packages/colorama/ansitowin32.py
venv/Lib/site-packages/colorama/initialise.py
venv/Lib/site-packages/colorama/win32.py
venv/Lib/site-packages/colorama/winterm.py
venv/Lib/site-packages/colorama/tests/__init__.py
venv/Lib/site-packages/colorama/tests/ansi_test.py
venv/Lib/site-packages/colorama/tests/ansitowin32_test.py
venv/Lib/site-packages/colorama/tests/initialise_test.py
venv/Lib/site-packages/colorama/tests/isatty_test.py
venv/Lib/site-packages/colorama/tests/utils.py
venv/Lib/site-packages/colorama/tests/winterm_test.py
venv/Lib/site-packages/packaging/__init__.py
venv/Lib/site-packages/packaging/_elffile.py
venv/Lib/site-packages/packaging/_manylinux.py
venv/Lib/site-packages/packaging/_musllinux.py
venv/Lib/site-packages/packaging/_parser.py
venv/Lib/site-packages/packaging/_structures.py
venv/Lib/site-packages/packaging/_tokenizer.py
venv/Lib/site-packages/packaging/markers.py
venv/Lib/site-packages/packaging/metadata.py
venv/Lib/site-packages/packaging/py.typed
venv/Lib/site-packages/packaging/requirements.py
venv/Lib/site-packages/packaging/specifiers.py
venv/Lib/site-packages/packaging/tags.py
venv/Lib/site-packages/packaging/utils.py
venv/Lib/site-packages/packaging/version.py
systel_bot-0.1.0.dist-info/LICENSE.txt
systel_bot-0.1.0.dist-info/METADATA
systel_bot-0.1.0.dist-info/WHEEL
systel_bot-0.1.0.dist-info/top_level.txt
systel_bot-0.1.0.dist-info/RECORD
