Metadata-Version: 2.1
Name: systel-bot
Version: 0.1.0
Summary: A Telegram bot that monitors system performance and sends updates.
Home-page: https://github.com/Dis-Co-der/systel-bot.git
Author: Dan Lappisto
Author-email: Dan Lappisto <lapitzlullaby@gmail.com>
Project-URL: Homepage, https://github.com/Dis-Co-der/systel-bot.git
Project-URL: Bug Tracker, https://github.com/Dis-Co-der/systel-bot/issues
Classifier: Programming Language :: Python :: 3
Classifier: License :: OSI Approved :: MIT License
Classifier: Operating System :: OS Independent
Requires-Python: >=3.6
License-File: LICENSE.txt
Requires-Dist: pip==24.2
Requires-Dist: setuptools==72.2.0
Requires-Dist: wheel==0.44.0
Requires-Dist: certifi==2024.7.4
Requires-Dist: charset-normalizer==3.3.2
Requires-Dist: GPUtil==1.4.0
Requires-Dist: idna==3.7
Requires-Dist: psutil==6.0.0
Requires-Dist: pynvml==11.5.3
Requires-Dist: python-dotenv==1.0.1
Requires-Dist: requests==2.32.3
Requires-Dist: schedule==1.2.2
Requires-Dist: urllib3==2.2.2
